hpxml_version_translator/__init__.py
hpxml_version_translator/__main__.py
hpxml_version_translator/change_namespace.xsl
hpxml_version_translator/converter.py
hpxml_version_translator/exceptions.py
hpxml_version_translator/schemas/v1.1.1/BaseElements.xsd
hpxml_version_translator/schemas/v1.1.1/HPXML.xsd
hpxml_version_translator/schemas/v1.1.1/HPXMLDataTypes.xsd
hpxml_version_translator/schemas/v1.1.1/MaintainBuilding.xsd
hpxml_version_translator/schemas/v1.1.1/MaintainConsumption.xsd
hpxml_version_translator/schemas/v1.1.1/MaintainContractor.xsd
hpxml_version_translator/schemas/v1.1.1/MaintainCustomer.xsd
hpxml_version_translator/schemas/v1.1.1/MaintainProject.xsd
hpxml_version_translator/schemas/v1.1.1/MaintainUtility.xsd
hpxml_version_translator/schemas/v2.3/BaseElements.xsd
hpxml_version_translator/schemas/v2.3/HPXML.xsd
hpxml_version_translator/schemas/v2.3/HPXMLDataTypes.xsd
hpxml_version_translator/schemas/v3.0/BaseElements.xsd
hpxml_version_translator/schemas/v3.0/HPXML.xsd
hpxml_version_translator/schemas/v3.0/HPXMLDataTypes.xsd
hpxml_version_translator/schemas/v4.0/BaseElements.xsd
hpxml_version_translator/schemas/v4.0/HPXML.xsd
hpxml_version_translator/schemas/v4.0/HPXMLDataTypes.xsd
hpxml_version_translator-1.0.1.dist-info/LICENSE
hpxml_version_translator-1.0.1.dist-info/METADATA
hpxml_version_translator-1.0.1.dist-info/WHEEL
hpxml_version_translator-1.0.1.dist-info/entry_points.txt
hpxml_version_translator-1.0.1.dist-info/top_level.txt
hpxml_version_translator-1.0.1.dist-info/RECORD
