Metadata-Version: 2.1
Name: hpxml-version-translator
Version: 1.0.1
Summary: Convert HPXML to newer version
Home-page: https://github.com/NREL/hpxml_version_translator
Author: Ben Park (NREL), Noel Merket (NREL), Scott Horowitz (NREL)
Author-email: ben.park@nrel.gov
License: UNKNOWN
Platform: UNKNOWN
Requires-Python: >=3.6
License-File: LICENSE
Requires-Dist: lxml
Requires-Dist: deprecated
Provides-Extra: dev
Requires-Dist: pytest (>=6.2) ; extra == 'dev'
Requires-Dist: pytest-mock ; extra == 'dev'
Requires-Dist: pytest-xdist ; extra == 'dev'
Requires-Dist: pytest-cov ; extra == 'dev'
Requires-Dist: flake8 ; extra == 'dev'
Requires-Dist: rope ; extra == 'dev'
Requires-Dist: black ; extra == 'dev'
